{
  "openapi": "3.0.4",
  "info": {
    "title": "IcdControl.Server",
    "version": "1.0"
  },
  "paths": {
    "/api/Icd/login": {
      "post": {
        "tags": [
          "Icd"
        ],
        "requestBody": {
          "content": {
            "application/json": {
              "schema": {
                "$ref": "#/components/schemas/LoginRequest"
              }
            },
            "text/json": {
              "schema": {
                "$ref": "#/components/schemas/LoginRequest"
              }
            },
            "application/*+json": {
              "schema": {
                "$ref": "#/components/schemas/LoginRequest"
              }
            }
          }
        },
        "responses": {
          "200": {
            "description": "OK"
          }
        }
      }
    },
    "/api/Icd/register": {
      "post": {
        "tags": [
          "Icd"
        ],
        "requestBody": {
          "content": {
            "application/json": {
              "schema": {
                "$ref": "#/components/schemas/RegisterRequest"
              }
            },
            "text/json": {
              "schema": {
                "$ref": "#/components/schemas/RegisterRequest"
              }
            },
            "application/*+json": {
              "schema": {
                "$ref": "#/components/schemas/RegisterRequest"
              }
            }
          }
        },
        "responses": {
          "200": {
            "description": "OK"
          }
        }
      }
    },
    "/api/Icd/save": {
      "post": {
        "tags": [
          "Icd"
        ],
        "requestBody": {
          "content": {
            "application/json": {
              "schema": {
                "$ref": "#/components/schemas/Icd"
              }
            },
            "text/json": {
              "schema": {
                "$ref": "#/components/schemas/Icd"
              }
            },
            "application/*+json": {
              "schema": {
                "$ref": "#/components/schemas/Icd"
              }
            }
          }
        },
        "responses": {
          "200": {
            "description": "OK"
          }
        }
      }
    },
    "/api/Icd/list": {
      "get": {
        "tags": [
          "Icd"
        ],
        "responses": {
          "200": {
            "description": "OK"
          }
        }
      }
    },
    "/api/Icd/{id}": {
      "get": {
        "tags": [
          "Icd"
        ],
        "parameters": [
          {
            "name": "id",
            "in": "path",
            "required": true,
            "schema": {
              "type": "string"
            }
          }
        ],
        "responses": {
          "200": {
            "description": "OK"
          }
        }
      }
    },
    "/api/Icd/{id}/export": {
      "get": {
        "tags": [
          "Icd"
        ],
        "parameters": [
          {
            "name": "id",
            "in": "path",
            "required": true,
            "schema": {
              "type": "string"
            }
          }
        ],
        "responses": {
          "200": {
            "description": "OK"
          }
        }
      }
    },
    "/api/Icd/admin/users": {
      "get": {
        "tags": [
          "Icd"
        ],
        "responses": {
          "200": {
            "description": "OK"
          }
        }
      }
    },
    "/api/Icd/admin/icd/{icdId}/permissions": {
      "get": {
        "tags": [
          "Icd"
        ],
        "parameters": [
          {
            "name": "icdId",
            "in": "path",
            "required": true,
            "schema": {
              "type": "string"
            }
          }
        ],
        "responses": {
          "200": {
            "description": "OK"
          }
        }
      }
    },
    "/api/Icd/admin/grant": {
      "post": {
        "tags": [
          "Icd"
        ],
        "requestBody": {
          "content": {
            "application/json": {
              "schema": {
                "$ref": "#/components/schemas/GrantRequest"
              }
            },
            "text/json": {
              "schema": {
                "$ref": "#/components/schemas/GrantRequest"
              }
            },
            "application/*+json": {
              "schema": {
                "$ref": "#/components/schemas/GrantRequest"
              }
            }
          }
        },
        "responses": {
          "200": {
            "description": "OK"
          }
        }
      }
    },
    "/WeatherForecast": {
      "get": {
        "tags": [
          "WeatherForecast"
        ],
        "operationId": "GetWeatherForecast",
        "responses": {
          "200": {
            "description": "OK",
            "content": {
              "text/plain": {
                "schema": {
                  "type": "array",
                  "items": {
                    "$ref": "#/components/schemas/WeatherForecast"
                  }
                }
              },
              "application/json": {
                "schema": {
                  "type": "array",
                  "items": {
                    "$ref": "#/components/schemas/WeatherForecast"
                  }
                }
              },
              "text/json": {
                "schema": {
                  "type": "array",
                  "items": {
                    "$ref": "#/components/schemas/WeatherForecast"
                  }
                }
              }
            }
          }
        }
      }
    }
  },
  "components": {
    "schemas": {
      "BaseField": {
        "type": "object",
        "properties": {
          "id": {
            "type": "string",
            "nullable": true
          },
          "name": {
            "type": "string",
            "nullable": true
          }
        },
        "additionalProperties": false
      },
      "GrantRequest": {
        "type": "object",
        "properties": {
          "userId": {
            "type": "string",
            "nullable": true
          },
          "icdId": {
            "type": "string",
            "nullable": true
          },
          "canEdit": {
            "type": "boolean"
          },
          "revoke": {
            "type": "boolean"
          }
        },
        "additionalProperties": false
      },
      "Icd": {
        "type": "object",
        "properties": {
          "icdId": {
            "type": "string",
            "nullable": true
          },
          "name": {
            "type": "string",
            "nullable": true
          },
          "version": {
            "type": "number",
            "format": "double"
          },
          "description": {
            "type": "string",
            "nullable": true
          },
          "messages": {
            "type": "array",
            "items": {
              "$ref": "#/components/schemas/Message"
            },
            "nullable": true
          },
          "structs": {
            "type": "array",
            "items": {
              "$ref": "#/components/schemas/Struct"
            },
            "nullable": true
          }
        },
        "additionalProperties": false
      },
      "LoginRequest": {
        "type": "object",
        "properties": {
          "username": {
            "type": "string",
            "nullable": true
          },
          "password": {
            "type": "string",
            "nullable": true
          }
        },
        "additionalProperties": false
      },
      "Message": {
        "type": "object",
        "properties": {
          "id": {
            "type": "string",
            "nullable": true
          },
          "name": {
            "type": "string",
            "nullable": true
          },
          "isUnion": {
            "type": "boolean"
          },
          "fields": {
            "type": "array",
            "items": {
              "$ref": "#/components/schemas/BaseField"
            },
            "nullable": true
          },
          "structType": {
            "type": "string",
            "nullable": true
          },
          "isRx": {
            "type": "boolean"
          },
          "isMsb": {
            "type": "boolean"
          },
          "description": {
            "type": "string",
            "nullable": true
          }
        },
        "additionalProperties": false
      },
      "RegisterRequest": {
        "type": "object",
        "properties": {
          "username": {
            "type": "string",
            "nullable": true
          },
          "email": {
            "type": "string",
            "nullable": true
          },
          "password": {
            "type": "string",
            "nullable": true
          }
        },
        "additionalProperties": false
      },
      "Struct": {
        "type": "object",
        "properties": {
          "id": {
            "type": "string",
            "nullable": true
          },
          "name": {
            "type": "string",
            "nullable": true
          },
          "isUnion": {
            "type": "boolean"
          },
          "fields": {
            "type": "array",
            "items": {
              "$ref": "#/components/schemas/BaseField"
            },
            "nullable": true
          },
          "structType": {
            "type": "string",
            "nullable": true
          }
        },
        "additionalProperties": false
      },
      "WeatherForecast": {
        "type": "object",
        "properties": {
          "date": {
            "type": "string",
            "format": "date"
          },
          "temperatureC": {
            "type": "integer",
            "format": "int32"
          },
          "temperatureF": {
            "type": "integer",
            "format": "int32",
            "readOnly": true
          },
          "summary": {
            "type": "string",
            "nullable": true
          }
        },
        "additionalProperties": false
      }
    }
  },
  "tags": [
    {
      "name": "Icd"
    },
    {
      "name": "WeatherForecast"
    }
  ]
}